hkj/__init__.py
hkj/sample.py
hkj-1.0.0.dist-info/RECORD
hkj-1.0.0.dist-info/metadata.json
hkj-1.0.0.dist-info/DESCRIPTION.rst
hkj-1.0.0.dist-info/METADATA
hkj-1.0.0.dist-info/WHEEL
hkj-1.0.0.dist-info/top_level.txt
